expert_kb/__init__.py
expert_kb/knowledgebase.py
expert_kb/py.typed
expert_kb/schema.sql
expert_kb/sqlite_db.py
expert_kb-0.1.1.dist-info/METADATA
expert_kb-0.1.1.dist-info/WHEEL
expert_kb-0.1.1.dist-info/top_level.txt
expert_kb-0.1.1.dist-info/RECORD
